detf/__init__.py
detf/arith/__init__.py
detf/arith/alpha_beta_filter.py
detf-0.0.2.dist-info/LICENSE
detf-0.0.2.dist-info/WHEEL
detf-0.0.2.dist-info/METADATA
detf-0.0.2.dist-info/RECORD
